afp/__init__.py
afp/afp.py
afp/api/__init__.py
afp/api/admin.py
afp/api/base.py
afp/api/margin_account.py
afp/api/product.py
afp/api/trading.py
afp/auth.py
afp/bindings/__init__.py
afp/bindings/auctioneer_facet.py
afp/bindings/bankruptcy_facet.py
afp/bindings/clearing_facet.py
afp/bindings/erc20.py
afp/bindings/facade.py
afp/bindings/final_settlement_facet.py
afp/bindings/margin_account.py
afp/bindings/margin_account_registry.py
afp/bindings/mark_price_tracker_facet.py
afp/bindings/oracle_provider.py
afp/bindings/product_registry.py
afp/bindings/system_viewer.py
afp/bindings/trading_protocol.py
afp/config.py
afp/constants.py
afp/decorators.py
afp/enums.py
afp/exceptions.py
afp/exchange.py
afp/hashing.py
afp/py.typed
afp/schemas.py
afp/validators.py
afp_sdk-0.5.4.dist-info/licenses/LICENSE
afp_sdk-0.5.4.dist-info/WHEEL
afp_sdk-0.5.4.dist-info/METADATA
afp_sdk-0.5.4.dist-info/RECORD
