Metadata-Version: 2.4
Name: afp-sdk
Version: 0.5.4
Summary: Autonomous Futures Protocol Python SDK
Keywords: autonity,web3,trading,crypto,prediction,forecast,markets
License-Expression: MIT
License-File: LICENSE
Classifier: Development Status :: 4 - Beta
Classifier: Programming Language :: Python
Classifier: Programming Language :: Python :: 3.11
Classifier: Programming Language :: Python :: 3.12
Classifier: Programming Language :: Python :: 3.13
Requires-Dist: decorator>=5.2.1
Requires-Dist: inflection>=0.5.1
Requires-Dist: pydantic>=2.10.6
Requires-Dist: requests>=2.32.0
Requires-Dist: siwe>=4.4.0
Requires-Dist: web3>=7.6.0
Requires-Python: >=3.11
Project-URL: Changes, https://github.com/autonity/afp-sdk/blob/master/CHANGELOG.md
Project-URL: Homepage, https://github.com/autonity/afp-sdk
Project-URL: Issues, https://github.com/autonity/afp-sdk/issues
Project-URL: Source, https://github.com/autonity/afp-sdk
